{"settings": {"FOCUSED_TIME": 35, "REST_TIME": 10}, "mros": {"name": "mros", "type": "task", "rank": 0, "deadline": 648000, "priority": 10.0, "next_window": "schedule_window", "creation": 1669650009.310792, "done": false, "duration": 180, "tot_focus": 0, "tot_rest": 0, "tot_idle": 0}, "work": {"name": "work", "type": "task", "rank": 0, "deadline": 648000, "priority": 5.0, "next_window": "schedule_window", "creation": 1669650040.94975, "done": false, "duration": 240, "tot_focus": 0, "tot_rest": 0, "tot_idle": 0}, "study": {"name": "study", "type": "task", "rank": 0, "deadline": 648000, "priority": 0.0, "next_window": "schedule_window", "creation": 1669650025.921427, "done": false, "duration": 120, "tot_focus": 0, "tot_rest": 0, "tot_idle": 0}}